README.md
setup.py
NotionBot.egg-info/PKG-INFO
NotionBot.egg-info/SOURCES.txt
NotionBot.egg-info/dependency_links.txt
NotionBot.egg-info/requires.txt
NotionBot.egg-info/top_level.txt
base/Base.py
base/Block.py
base/Database.py
base/Page.py
base/__init__.py
object/BlockObject.py
object/CheckBox.py
object/Color.py
object/Date.py
object/Emoji.py
object/File.py
object/Link.py
object/NotionObject.py
object/Number.py
object/Option.py
object/Properties.py
object/Query.py
object/Relation.py
object/Search.py
object/Syntax.py
object/Text.py
object/__init__.py
test/__init__.py
test/test_Database.py
test/test_NotionClient.py
test/test_Page.py