Metadata-Version: 2.1
Name: NotionBot
Version: 0.0.3
Summary: Wrapper around Notion API.
Home-page: https://github.com/quan0715/PyNotion
Author: Quan
Author-email: quan787887@gmail.com
License: license.txt
